BehaviorPattern
