Metadata-Version: 2.1
Name: BehaviorPattern
Version: 0.0.7
Summary: The tool is designed to mine behavior patterns
Author: Chen Chen
Author-email: cchen56@163.com
Classifier: Programming Language :: Python :: 3
Classifier: Operating System :: OS Independent
Requires-Python: >=3.6
